pydantic_pynamodb/__init__.py
pydantic_pynamodb/py.typed
pydantic_pynamodb-0.1.0.dist-info/LICENSE.rst
pydantic_pynamodb-0.1.0.dist-info/METADATA
pydantic_pynamodb-0.1.0.dist-info/WHEEL
pydantic_pynamodb-0.1.0.dist-info/RECORD
