Metadata-Version: 2.1
Name: pydantic-pynamodb
Version: 0.1.0
Summary: Pydantic Pynamodb
Home-page: https://github.com/andrewthetechie/pydantic-pynamodb
License: MIT
Author: Andrew Herrington
Author-email: andrew.the.techie@gmail.com
Requires-Python: >=3.7,<4.0
Classifier: Development Status :: 3 - Alpha
Classifier: License :: OSI Approved :: MIT License
Classifier: Programming Language :: Python :: 3
Classifier: Programming Language :: Python :: 3.7
Classifier: Programming Language :: Python :: 3.8
Classifier: Programming Language :: Python :: 3.9
Classifier: Programming Language :: Python :: 3.10
Classifier: Programming Language :: Python :: 3.11
Requires-Dist: pydantic (>=1.9.0,<2.0.0)
Requires-Dist: pynamodb (>=5.2.0,<6.0.0)
Project-URL: Changelog, https://github.com/andrewthetechie/pydantic-pynamodb/releases
Project-URL: Documentation, https://pydantic-pynamodb.readthedocs.io
Project-URL: Repository, https://github.com/andrewthetechie/pydantic-pynamodb
